Metadata-Version: 2.1
Name: pydiscordself
Version: 0.2
Summary: Cette librairie permet de créer des selfbots Discord.
Home-page: https://github.com/8borane8/pydiscordself
Author: borane
License: ISC
Keywords: discord,selfbot
Requires-Python: >=3.6
License-File: LICENSE.md
